marqstree_mcp_demo/__init__.py
marqstree_mcp_demo-0.1.0.dist-info/WHEEL
marqstree_mcp_demo-0.1.0.dist-info/entry_points.txt
marqstree_mcp_demo-0.1.0.dist-info/METADATA
marqstree_mcp_demo-0.1.0.dist-info/RECORD
