Metadata-Version: 2.3
Name: marqstree-mcp-demo
Version: 0.1.0
Summary: Add your description here
Author: hothotsavage
Author-email: hothotsavage <1725288552@qq.com>
Requires-Dist: mcp[cli]>=1.18.0
Requires-Python: >=3.13
